[{"user":"jncorrea","avatar":"","sexo":"Femenino","id_user":"6","fecha_not":"2015-09-11T17:26:30-0500","visto":"1","id_grupo":"2","nom_grupo":"Amigos","mensaje":"ha comentado en el grupo","id_noti":"2"},{"user":"jncorrea","avatar":"","sexo":"Femenino","id_user":"2","fecha_not":"2015-09-15T11:21:19-0500","visto":"0","id_grupo":"5","nom_grupo":"holaaa","mensaje":"ha comentado en el grupo","id_noti":"45"},{"user":"jncorrea","avatar":"","sexo":"Femenino","id_user":"6","fecha_not":"2015-09-15T11:22:50-0500","visto":"0","id_grupo":"5","nom_grupo":"holaaa","mensaje":"ha comentado en el grupo","id_noti":"53"},{"user":"jncorrea","avatar":"","sexo":"Femenino","id_user":"2","fecha_not":"2015-09-15T11:22:50-0500","visto":"0","id_grupo":"5","nom_grupo":"holaaa","mensaje":"ha comentado en el grupo","id_noti":"54"},{"user":"jncorrea","avatar":"","sexo":"Femenino","id_user":"6","fecha_not":"2015-09-15T11:35:03-0500","visto":"0","id_grupo":"5","nom_grupo":"holaaa","mensaje":"ha comentado en el grupo","id_noti":"57"},{"user":"jncorrea","avatar":"","sexo":"Femenino","id_user":"2","fecha_not":"2015-09-15T11:35:03-0500","visto":"0","id_grupo":"5","nom_grupo":"holaaa","mensaje":"ha comentado en el grupo","id_noti":"58"},{"user":"jncorrea","avatar":"","sexo":"Femenino","id_user":"5","fecha_not":"2015-09-15T11:35:03-0500","visto":"0","id_grupo":"5","nom_grupo":"holaaa","mensaje":"ha comentado en el grupo","id_noti":"59"},{"user":"jncorrea","avatar":"","sexo":"Femenino","id_user":"6","fecha_not":"2015-09-15T13:01:46-0500","visto":"0","id_grupo":"5","nom_grupo":"holaaa","mensaje":"ha comentado en el grupo","id_noti":"94"},{"user":"jncorrea","avatar":"","sexo":"Femenino","id_user":"2","fecha_not":"2015-09-15T13:01:46-0500","visto":"0","id_grupo":"5","nom_grupo":"holaaa","mensaje":"ha comentado en el grupo","id_noti":"95"},{"user":"jncorrea","avatar":"","sexo":"Femenino","id_user":"5","fecha_not":"2015-09-15T13:01:46-0500","visto":"0","id_grupo":"5","nom_grupo":"holaaa","mensaje":"ha comentado en el grupo","id_noti":"96"},{"user":"esquezada","avatar":"\/user.jpeg","sexo":"Masculino","id_user":"6","fecha_not":"2015-09-15T11:21:49-0500","visto":"0","id_grupo":"5","nom_grupo":"holaaa","mensaje":"ha comentado en el grupo","id_noti":"48"},{"user":"esquezada","avatar":"\/user.jpeg","sexo":"Masculino","id_user":"2","fecha_not":"2015-09-15T11:21:49-0500","visto":"0","id_grupo":"5","nom_grupo":"holaaa","mensaje":"ha comentado en el grupo","id_noti":"49"},{"user":"jncorrea93","avatar":"\/user.jpeg","sexo":"Femenino","id_user":"2","fecha_not":"2015-09-11T17:34:26-0500","visto":"0","id_grupo":"2","nom_grupo":"Amigos","mensaje":"ha comentado en el grupo","id_noti":"3"},{"user":"jncorrea93","avatar":"\/user.jpeg","sexo":"Femenino","id_user":"2","fecha_not":"2015-09-15T12:03:58-0500","visto":"0","id_grupo":"2","nom_grupo":"Amigos","mensaje":"ha comentado en el grupo","id_noti":"70"},{"user":"jncorrea93","avatar":"\/user.jpeg","sexo":"Femenino","id_user":"1","fecha_not":"2015-09-15T12:03:58-0500","visto":"0","id_grupo":"2","nom_grupo":"Amigos","mensaje":"ha comentado en el grupo","id_noti":"71"},{"user":"jncorrea93","avatar":"\/user.jpeg","sexo":"Femenino","id_user":"2","fecha_not":"2015-09-15T12:13:46-0500","visto":"0","id_grupo":"2","nom_grupo":"Amigos","mensaje":"ha comentado en el grupo","id_noti":"84"},{"user":"jncorrea93","avatar":"\/user.jpeg","sexo":"Femenino","id_user":"1","fecha_not":"2015-09-15T12:13:46-0500","visto":"0","id_grupo":"2","nom_grupo":"Amigos","mensaje":"ha comentado en el grupo","id_noti":"85"},{"user":"jncorrea93","avatar":"\/user.jpeg","sexo":"Femenino","id_user":"2","fecha_not":"2015-09-15T12:53:22-0500","visto":"0","id_grupo":"2","nom_grupo":"Amigos","mensaje":"ha comentado en el grupo","id_noti":"90"},{"user":"jncorrea93","avatar":"\/user.jpeg","sexo":"Femenino","id_user":"1","fecha_not":"2015-09-15T12:53:22-0500","visto":"0","id_grupo":"2","nom_grupo":"Amigos","mensaje":"ha comentado en el grupo","id_noti":"91"},{"user":"jncorrea93","avatar":"\/user.jpeg","sexo":"Femenino","id_user":"2","fecha_not":"2015-09-15T13:00:19-0500","visto":"0","id_grupo":"2","nom_grupo":"Amigos","mensaje":"ha comentado en el grupo","id_noti":"92"},{"user":"jncorrea93","avatar":"\/user.jpeg","sexo":"Femenino","id_user":"1","fecha_not":"2015-09-15T13:00:19-0500","visto":"0","id_grupo":"2","nom_grupo":"Amigos","mensaje":"ha comentado en el grupo","id_noti":"93"},{"user":"jncorrea93","avatar":"\/user.jpeg","sexo":"Femenino","id_user":"2","fecha_not":"2015-09-15T11:22:09-0500","visto":"0","id_grupo":"5","nom_grupo":"holaaa","mensaje":"ha comentado en el grupo","id_noti":"51"},{"user":"jncorrea93","avatar":"\/user.jpeg","sexo":"Femenino","id_user":"5","fecha_not":"2015-09-15T11:22:09-0500","visto":"0","id_grupo":"5","nom_grupo":"holaaa","mensaje":"ha comentado en el grupo","id_noti":"52"}]